LICENSE.txt
MANIFEST.in
README.rst
runtests.py
setup.py
mpower/__init__.py
mpower/__init__.pyc
mpower/direct_payments.py
mpower/direct_payments.pyc
mpower/invoice.py
mpower/invoice.pyc
mpower/opr.py
mpower/opr.pyc
mpower.egg-info/PKG-INFO
mpower.egg-info/SOURCES.txt
mpower.egg-info/dependency_links.txt
mpower.egg-info/requires.txt
mpower.egg-info/top_level.txt
tests/__init__.py
tests/test_direct_payments.py
tests/test_general.py
tests/test_invoice.py
tests/test_opr.py