Metadata-Version: 1.1
Name: mpower
Version: 0.1.1
Summary: MPower Payments Python client library
Home-page: https://github.com/mawuli/mpower-python
Author: Mawuli Adzaku
Author-email: mawuli@mawuli.me
License: LICENSE.txt
Keywords: mpower mobile money payments
Platform: UNKNOWN
Classifier: Development Status :: 2 - Pre-Alpha
Classifier: Intended Audience :: Developers
Classifier: Topic :: Utilities
Classifier: License :: OSI Approved :: MIT License
